hdintegrator.py
setup.py
hdintegrator.egg-info/PKG-INFO
hdintegrator.egg-info/SOURCES.txt
hdintegrator.egg-info/dependency_links.txt
hdintegrator.egg-info/requires.txt
hdintegrator.egg-info/top_level.txt
integrands/N-sphere.py
submodules/ndgrid/source/cell.py
submodules/ndgrid/source/ndgrid.py