Metadata-Version: 1.2
Name: hdintegrator
Version: 1.0
Summary: High-Dimensional Integrator, see github.com/iljah/hdintegrator for full version
Home-page: https://github.com/iljah/hdintegrator
Author: Ilja Honkonen
Author-email: ilja.honkonen@fmi.fi
License: UNKNOWN
Platform: UNKNOWN
Classifier: Development Status :: 5 - Production/Stable
Classifier: Environment :: Console
Classifier: Intended Audience :: Science/Research
Classifier: License :: OSI Approved :: GNU General Public License v3 or later (GPLv3+)
Classifier: Natural Language :: English
Classifier: Operating System :: Unix
Classifier: Programming Language :: Python :: 3
Classifier: Topic :: Scientific/Engineering :: Mathematics
Requires-Python: >=3
